mbusread/__init__.py
mbusread/i18n.py
mbusread/logger.py
mbusread/mbus_config.py
mbusread/mbus_mqtt.py
mbusread/mbus_parser.py
mbusread/mbus_reader.py
mbusread/mbus_reader_cmd.py
mbusread/mbus_viewer.py
mbusread/mbus_viewer_cmd.py
mbusread/mbus_viewer_server.py
mbusread/version.py
mbusread_examples/i18n.yaml
mbusread_examples/mbus_config.yaml
mbusread_examples/mbus_io_config.yaml
mbusread_examples/mqtt_config.yaml
mbusreader-0.1.0.dist-info/METADATA
mbusreader-0.1.0.dist-info/WHEEL
mbusreader-0.1.0.dist-info/entry_points.txt
mbusreader-0.1.0.dist-info/licenses/LICENSE
mbusreader-0.1.0.dist-info/RECORD
