Metadata-Version: 2.4
Name: mbusreader
Version: 0.1.0
Summary: M-Bus reader tool
Project-URL: Home, https://github.com/WolfgangFahl/mbusreader
Project-URL: Documentation, https://wiki.bitplan.com/index.php/MBus_Reader
Project-URL: Source, https://github.com/WolfgangFahl/mbusreader
Author-email: Wolfgang Fahl <wf@bitplan.com>
Maintainer-email: Wolfgang Fahl <wf@bitplan.com>
License-Expression: Apache-2.0
License-File: LICENSE
Keywords: components,nicegui,ui
Classifier: Development Status :: 4 - Beta
Classifier: Environment :: Console
Classifier: Intended Audience :: Developers
Classifier: Intended Audience :: Education
Classifier: License :: OSI Approved :: Apache Software License
Classifier: Operating System :: OS Independent
Classifier: Programming Language :: Python :: 3 :: Only
Classifier: Programming Language :: Python :: 3.10
Classifier: Programming Language :: Python :: 3.11
Classifier: Programming Language :: Python :: 3.12
Classifier: Programming Language :: Python :: 3.13
Classifier: Topic :: Software Development :: Libraries :: Python Modules
Requires-Python: >=3.9
Requires-Dist: paho-mqtt>=2.1.0
Requires-Dist: pybasemkit>=0.0.3
Requires-Dist: pymeterbus>=0.8.4
Provides-Extra: gui
Requires-Dist: ngwidgets>=0.27.0; extra == 'gui'
Provides-Extra: test
Requires-Dist: green; extra == 'test'
Provides-Extra: yaml
Requires-Dist: dacite>=1.8.1; extra == 'yaml'
Requires-Dist: dataclasses-json>=0.6.3; extra == 'yaml'
Requires-Dist: pyyaml>=6.0.1; extra == 'yaml'
